<?xml version="1.0" encoding="ISO-8859-1" ?>
<?xml-stylesheet type="text/xsl" href="drcss.xsl"?>
<drcreport>
  <header>POEM_RS485_Controller_sb</header>
  <drc>
    <status>C:\Microchip\Libero_SoC_v2023.1\Designer/data/drcreport\warn.png</status>
    <StatusMessage>Warning</StatusMessage>
    <message> bus interface data width mismatch</message>
    <detail> There is a data width mismatch between CoreAPB3_C0_0:APBmslave0:PWDATAS[0-31] and Controller_Interface_0:BIF_1:BIF_1_PWDATA[0-15] which may result in a loss of data.</detail>
    <crossprobe>liberoaction://cross_probe/smartdesign/POEM_RS485_Controller_sb/pins/CoreAPB3_C0_0:APBmslave0</crossprobe>
  </drc>
</drcreport>
